geoproximity/__init__.py
geoproximity/geoproximity.py
geoproximity/polygon_area.py
geoproximity-0.1.dist-info/LICENSE
geoproximity-0.1.dist-info/METADATA
geoproximity-0.1.dist-info/WHEEL
geoproximity-0.1.dist-info/top_level.txt
geoproximity-0.1.dist-info/RECORD
