Metadata-Version: 2.1
Name: geoproximity
Version: 0.1
Summary: A Python package for geospatial distance calculations and proximity-related functions.
Home-page: https://github.com/nrjadkry/geoproximity
Author: Niraj Adhikari
Author-email: nrjadkry@gmail.com
Classifier: Development Status :: 3 - Alpha
Classifier: Intended Audience :: Developers
Classifier: License :: OSI Approved :: MIT License
Classifier: Topic :: Scientific/Engineering :: GIS
Classifier: Programming Language :: Python :: 3.8
License-File: LICENSE
